mdforest/__init__.py
mdforest/mdforest.py
mdforest/treebuild.py
mdforest/tree/__init__.py
mdforest/tree/types.py
mdforest-1.6.3.dist-info/LICENSE
mdforest-1.6.3.dist-info/METADATA
mdforest-1.6.3.dist-info/WHEEL
mdforest-1.6.3.dist-info/top_level.txt
mdforest-1.6.3.dist-info/RECORD
