Metadata-Version: 2.1
Name: mdforest
Version: 1.6.3
Summary: A package to convert between Markdown and a forest data structure for efficient processing.
Home-page: http://github.com/kj3moraes/mdforest
Download-URL: https://github.com/kj3moraes/mdforest/archive/1.6.3.zip
Author: Keane Moraes
Author-email: lordvader3002@gmail.com
License: Apache 2.0
Classifier: Topic :: Utilities
License-File: LICENSE
Requires-Dist: markdown
Requires-Dist: beautifulsoup4
Requires-Dist: python-frontmatter
